{"schemaVersion":1,"academicYear":"2027","universityCode":"0000233","university":"화성의과학대학교","campus":"본교","historyUniversityCodes":["0000233"],"options":[{"optionId":"OPT27-21059cdfe856cb37","entityId":"ENT27-867f34cab78d4626","department":"간호학과","admissionName":"학생부 교과 우수자전형","category":"학생부위주(교과)","connectionStatus":"review_required","connectionLabel":"명칭·전형 변경 가능성 검토","matchMethod":"manual_review_candidates","approvedYears":[],"approvedHistoryIds":[],"approvedHistoryUniversityCodes":[],"reviewCandidateCount":3,"candidates":[{"relation":"admission_changed_candidate","reviewStatus":"manual_review","matchMethod":"exact_department_changed_admission","score":0.72,"departmentScore":1.0,"admissionScore":0.0,"department":"간호학과","admission":"기초생활수급자 및 차상위계층전형","category":"학생부교과","historicalYears":["2024","2025","2026"],"historicalRecordIds":["ADIGA-0000233-2024-SUBJECT-3-5-간호학과","ADIGA-0000233-2025-SUBJECT-3-8-간호학과","ADIGA-0000233-2026-SUBJECT-3-4-간호학과"],"historicalUniversityCodes":["0000233"],"sourceUrls":["https://www.adiga.kr/ucp/uvt/uni/univDetailSelection.do?menuId=PCUVTINF2000&searchSyr=2025&unvCd=0000233","https://www.adiga.kr/ucp/uvt/uni/univDetailSelection.do?menuId=PCUVTINF2000&searchSyr=2026&unvCd=0000233","https://www.adiga.kr/ucp/uvt/uni/univDetailSelection.do?menuId=PCUVTINF2000&searchSyr=2027&unvCd=0000233"],"candidateId":"CAND-c43c32b9ecbc4d20"},{"relation":"admission_changed_candidate","reviewStatus":"manual_review","matchMethod":"exact_department_changed_admission","score":0.72,"departmentScore":1.0,"admissionScore":0.0,"department":"간호학과","admission":"농어촌학생전형","category":"학생부교과","historicalYears":["2024","2025","2026"],"historicalRecordIds":["ADIGA-0000233-2024-SUBJECT-4-4-간호학과","ADIGA-0000233-2025-SUBJECT-4-5-간호학과","ADIGA-0000233-2026-SUBJECT-4-4-간호학과"],"historicalUniversityCodes":["0000233"],"sourceUrls":["https://www.adiga.kr/ucp/uvt/uni/univDetailSelection.do?menuId=PCUVTINF2000&searchSyr=2025&unvCd=0000233","https://www.adiga.kr/ucp/uvt/uni/univDetailSelection.do?menuId=PCUVTINF2000&searchSyr=2026&unvCd=0000233","https://www.adiga.kr/ucp/uvt/uni/univDetailSelection.do?menuId=PCUVTINF2000&searchSyr=2027&unvCd=0000233"],"candidateId":"CAND-5d30ed754ede66fc"},{"relation":"admission_changed_candidate","reviewStatus":"manual_review","matchMethod":"exact_department_changed_admission","score":0.72,"departmentScore":1.0,"admissionScore":0.0,"department":"간호학과","admission":"일반학생전형","category":"학생부교과","historicalYears":["2024","2025","2026"],"historicalRecordIds":["ADIGA-0000233-2024-SUBJECT-1-6-간호학과","ADIGA-0000233-2025-SUBJECT-1-10-간호학과","ADIGA-0000233-2026-SUBJECT-1-10-간호학과"],"historicalUniversityCodes":["0000233"],"sourceUrls":["https://www.adiga.kr/ucp/uvt/uni/univDetailSelection.do?menuId=PCUVTINF2000&searchSyr=2025&unvCd=0000233","https://www.adiga.kr/ucp/uvt/uni/univDetailSelection.do?menuId=PCUVTINF2000&searchSyr=2026&unvCd=0000233","https://www.adiga.kr/ucp/uvt/uni/univDetailSelection.do?menuId=PCUVTINF2000&searchSyr=2027&unvCd=0000233"],"candidateId":"CAND-14015f84f0ce7583"}]},{"optionId":"OPT27-a9da3224096f1df9","entityId":"ENT27-24c30aa1d35d3b01","department":"간호학과","admissionName":"학생부 교과(기초생활수급자, 차상위계층, 한부모가족 지원 대상자 특별전형)","category":"학생부위주(교과)","connectionStatus":"review_required","connectionLabel":"명칭·전형 변경 가능성 검토","matchMethod":"manual_review_candidates","approvedYears":[],"approvedHistoryIds":[],"approvedHistoryUniversityCodes":[],"reviewCandidateCount":3,"candidates":[{"relation":"admission_changed_candidate","reviewStatus":"manual_review","matchMethod":"exact_department_changed_admission","score":0.8897,"departmentScore":1.0,"admissionScore":0.6061,"department":"간호학과","admission":"기초생활수급자 및 차상위계층전형","category":"학생부교과","historicalYears":["2024","2025","2026"],"historicalRecordIds":["ADIGA-0000233-2024-SUBJECT-3-5-간호학과","ADIGA-0000233-2025-SUBJECT-3-8-간호학과","ADIGA-0000233-2026-SUBJECT-3-4-간호학과"],"historicalUniversityCodes":["0000233"],"sourceUrls":["https://www.adiga.kr/ucp/uvt/uni/univDetailSelection.do?menuId=PCUVTINF2000&searchSyr=2025&unvCd=0000233","https://www.adiga.kr/ucp/uvt/uni/univDetailSelection.do?menuId=PCUVTINF2000&searchSyr=2026&unvCd=0000233","https://www.adiga.kr/ucp/uvt/uni/univDetailSelection.do?menuId=PCUVTINF2000&searchSyr=2027&unvCd=0000233"],"candidateId":"CAND-8d7b8097e1ab2586"},{"relation":"admission_changed_candidate","reviewStatus":"manual_review","matchMethod":"exact_department_changed_admission","score":0.72,"departmentScore":1.0,"admissionScore":0.0,"department":"간호학과","admission":"농어촌학생전형","category":"학생부교과","historicalYears":["2024","2025","2026"],"historicalRecordIds":["ADIGA-0000233-2024-SUBJECT-4-4-간호학과","ADIGA-0000233-2025-SUBJECT-4-5-간호학과","ADIGA-0000233-2026-SUBJECT-4-4-간호학과"],"historicalUniversityCodes":["0000233"],"sourceUrls":["https://www.adiga.kr/ucp/uvt/uni/univDetailSelection.do?menuId=PCUVTINF2000&searchSyr=2025&unvCd=0000233","https://www.adiga.kr/ucp/uvt/uni/univDetailSelection.do?menuId=PCUVTINF2000&searchSyr=2026&unvCd=0000233","https://www.adiga.kr/ucp/uvt/uni/univDetailSelection.do?menuId=PCUVTINF2000&searchSyr=2027&unvCd=0000233"],"candidateId":"CAND-be208bfc30a9c8c0"},{"relation":"admission_changed_candidate","reviewStatus":"manual_review","matchMethod":"exact_department_changed_admission","score":0.72,"departmentScore":1.0,"admissionScore":0.0,"department":"간호학과","admission":"일반학생전형","category":"학생부교과","historicalYears":["2024","2025","2026"],"historicalRecordIds":["ADIGA-0000233-2024-SUBJECT-1-6-간호학과","ADIGA-0000233-2025-SUBJECT-1-10-간호학과","ADIGA-0000233-2026-SUBJECT-1-10-간호학과"],"historicalUniversityCodes":["0000233"],"sourceUrls":["https://www.adiga.kr/ucp/uvt/uni/univDetailSelection.do?menuId=PCUVTINF2000&searchSyr=2025&unvCd=0000233","https://www.adiga.kr/ucp/uvt/uni/univDetailSelection.do?menuId=PCUVTINF2000&searchSyr=2026&unvCd=0000233","https://www.adiga.kr/ucp/uvt/uni/univDetailSelection.do?menuId=PCUVTINF2000&searchSyr=2027&unvCd=0000233"],"candidateId":"CAND-22a282a6f1ada266"}]},{"optionId":"OPT27-4edacccf419e390c","entityId":"ENT27-2a2531ec6566a20a","department":"간호학과","admissionName":"학생부 교과(농어촌학생전형)","category":"학생부위주(교과)","connectionStatus":"approved_exact","connectionLabel":"동일 모집단위·전형명 확인","matchMethod":"exact_normalized_identity","approvedYears":["2024","2025","2026"],"approvedHistoryIds":["ADIGA-0000233-2024-SUBJECT-4-4-간호학과","ADIGA-0000233-2025-SUBJECT-4-5-간호학과","ADIGA-0000233-2026-SUBJECT-4-4-간호학과"],"approvedHistoryUniversityCodes":["0000233"],"reviewCandidateCount":0,"candidates":[]},{"optionId":"OPT27-13b11f7f69befd94","entityId":"ENT27-21a713f048f9854a","department":"간호학과","admissionName":"학생부 교과(특성화고교 졸업자 특별전형)","category":"학생부위주(교과)","connectionStatus":"approved_exact","connectionLabel":"동일 모집단위·전형명 확인","matchMethod":"exact_normalized_identity","approvedYears":["2024","2025","2026"],"approvedHistoryIds":["ADIGA-0000233-2024-SUBJECT-2-4-간호학과","ADIGA-0000233-2025-SUBJECT-2-5-간호학과","ADIGA-0000233-2026-SUBJECT-2-4-간호학과"],"approvedHistoryUniversityCodes":["0000233"],"reviewCandidateCount":0,"candidates":[]},{"optionId":"OPT27-5ae3eefeb230d6a8","entityId":"ENT27-ad51e5430751339e","department":"경찰과학수사학과","admissionName":"학생부 교과 우수자전형","category":"학생부위주(교과)","connectionStatus":"review_required","connectionLabel":"명칭·전형 변경 가능성 검토","matchMethod":"manual_review_candidates","approvedYears":[],"approvedHistoryIds":[],"approvedHistoryUniversityCodes":[],"reviewCandidateCount":3,"candidates":[{"relation":"admission_changed_candidate","reviewStatus":"manual_review","matchMethod":"exact_department_changed_admission","score":0.72,"departmentScore":1.0,"admissionScore":0.0,"department":"경찰과학수사학과","admission":"기초생활수급자 및 차상위계층전형","category":"학생부교과","historicalYears":["2025"],"historicalRecordIds":["ADIGA-0000233-2025-SUBJECT-3-11-경찰과학수사학과"],"historicalUniversityCodes":["0000233"],"sourceUrls":["https://www.adiga.kr/ucp/uvt/uni/univDetailSelection.do?menuId=PCUVTINF2000&searchSyr=2026&unvCd=0000233"],"candidateId":"CAND-cdc8ab59848f5fb8"},{"relation":"admission_changed_candidate","reviewStatus":"manual_review","matchMethod":"exact_department_changed_admission","score":0.72,"departmentScore":1.0,"admissionScore":0.0,"department":"경찰과학수사학과","admission":"기회균형전형","category":"학생부교과","historicalYears":["2026"],"historicalRecordIds":["ADIGA-0000233-2026-SUBJECT-5-10-경찰과학수사학과"],"historicalUniversityCodes":["0000233"],"sourceUrls":["https://www.adiga.kr/ucp/uvt/uni/univDetailSelection.do?menuId=PCUVTINF2000&searchSyr=2027&unvCd=0000233"],"candidateId":"CAND-fc62d993aac1fd4b"},{"relation":"admission_changed_candidate","reviewStatus":"manual_review","matchMethod":"exact_department_changed_admission","score":0.72,"departmentScore":1.0,"admissionScore":0.0,"department":"경찰과학수사학과","admission":"농어촌학생전형","category":"학생부교과","historicalYears":["2026"],"historicalRecordIds":["ADIGA-0000233-2026-SUBJECT-4-5-경찰과학수사학과"],"historicalUniversityCodes":["0000233"],"sourceUrls":["https://www.adiga.kr/ucp/uvt/uni/univDetailSelection.do?menuId=PCUVTINF2000&searchSyr=2027&unvCd=0000233"],"candidateId":"CAND-f6f64ecb3efa9045"}]},{"optionId":"OPT27-575bf2a61eca5d63","entityId":"ENT27-42a8e7d45672a03c","department":"경찰과학수사학과","admissionName":"학생부 교과(기회균형선발 특별전형)","category":"학생부위주(교과)","connectionStatus":"review_required","connectionLabel":"명칭·전형 변경 가능성 검토","matchMethod":"manual_review_candidates","approvedYears":[],"approvedHistoryIds":[],"approvedHistoryUniversityCodes":[],"reviewCandidateCount":3,"candidates":[{"relation":"admission_changed_candidate","reviewStatus":"manual_review","matchMethod":"exact_department_changed_admission","score":0.93,"departmentScore":1.0,"admissionScore":0.75,"department":"경찰과학수사학과","admission":"기회균형전형","category":"학생부교과","historicalYears":["2026"],"historicalRecordIds":["ADIGA-0000233-2026-SUBJECT-5-10-경찰과학수사학과"],"historicalUniversityCodes":["0000233"],"sourceUrls":["https://www.adiga.kr/ucp/uvt/uni/univDetailSelection.do?menuId=PCUVTINF2000&searchSyr=2027&unvCd=0000233"],"candidateId":"CAND-265b2b6c31e24901"},{"relation":"admission_changed_candidate","reviewStatus":"manual_review","matchMethod":"exact_department_changed_admission","score":0.72,"departmentScore":1.0,"admissionScore":0.0,"department":"경찰과학수사학과","admission":"기초생활수급자 및 차상위계층전형","category":"학생부교과","historicalYears":["2025"],"historicalRecordIds":["ADIGA-0000233-2025-SUBJECT-3-11-경찰과학수사학과"],"historicalUniversityCodes":["0000233"],"sourceUrls":["https://www.adiga.kr/ucp/uvt/uni/univDetailSelection.do?menuId=PCUVTINF2000&searchSyr=2026&unvCd=0000233"],"candidateId":"CAND-560c41ec1535aabb"},{"relation":"admission_changed_candidate","reviewStatus":"manual_review","matchMethod":"exact_department_changed_admission","score":0.72,"departmentScore":1.0,"admissionScore":0.0,"department":"경찰과학수사학과","admission":"농어촌학생전형","category":"학생부교과","historicalYears":["2026"],"historicalRecordIds":["ADIGA-0000233-2026-SUBJECT-4-5-경찰과학수사학과"],"historicalUniversityCodes":["0000233"],"sourceUrls":["https://www.adiga.kr/ucp/uvt/uni/univDetailSelection.do?menuId=PCUVTINF2000&searchSyr=2027&unvCd=0000233"],"candidateId":"CAND-bff7ff06929a608d"}]},{"optionId":"OPT27-6d201976950fe556","entityId":"ENT27-642266052f32b47b","department":"데이터사이언스학과","admissionName":"학생부 교과 우수자전형","category":"학생부위주(교과)","connectionStatus":"review_required","connectionLabel":"명칭·전형 변경 가능성 검토","matchMethod":"manual_review_candidates","approvedYears":[],"approvedHistoryIds":[],"approvedHistoryUniversityCodes":[],"reviewCandidateCount":3,"candidates":[{"relation":"admission_changed_candidate","reviewStatus":"manual_review","matchMethod":"exact_department_changed_admission","score":0.72,"departmentScore":1.0,"admissionScore":0.0,"department":"데이터사이언스학과","admission":"기회균형전형","category":"학생부교과","historicalYears":["2026"],"historicalRecordIds":["ADIGA-0000233-2026-SUBJECT-5-7-데이터사이언스학과"],"historicalUniversityCodes":["0000233"],"sourceUrls":["https://www.adiga.kr/ucp/uvt/uni/univDetailSelection.do?menuId=PCUVTINF2000&searchSyr=2027&unvCd=0000233"],"candidateId":"CAND-96bd0c310a410e77"},{"relation":"admission_changed_candidate","reviewStatus":"manual_review","matchMethod":"exact_department_changed_admission","score":0.72,"departmentScore":1.0,"admissionScore":0.0,"department":"데이터사이언스학과","admission":"일반학생전형","category":"학생부교과","historicalYears":["2024","2025","2026"],"historicalRecordIds":["ADIGA-0000233-2024-SUBJECT-1-13-데이터사이언스학과","ADIGA-0000233-2025-SUBJECT-1-14-데이터사이언스학과","ADIGA-0000233-2026-SUBJECT-1-11-데이터사이언스학과"],"historicalUniversityCodes":["0000233"],"sourceUrls":["https://www.adiga.kr/ucp/uvt/uni/univDetailSelection.do?menuId=PCUVTINF2000&searchSyr=2025&unvCd=0000233","https://www.adiga.kr/ucp/uvt/uni/univDetailSelection.do?menuId=PCUVTINF2000&searchSyr=2026&unvCd=0000233","https://www.adiga.kr/ucp/uvt/uni/univDetailSelection.do?menuId=PCUVTINF2000&searchSyr=2027&unvCd=0000233"],"candidateId":"CAND-4bc2055610730aa5"},{"relation":"admission_changed_candidate","reviewStatus":"manual_review","matchMethod":"exact_department_changed_admission","score":0.72,"departmentScore":1.0,"admissionScore":0.0,"department":"데이터사이언스학과","admission":"특성화고교 졸업자전형","category":"학생부교과","historicalYears":["2025"],"historicalRecordIds":["ADIGA-0000233-2025-SUBJECT-2-4-데이터사이언스학과"],"historicalUniversityCodes":["0000233"],"sourceUrls":["https://www.adiga.kr/ucp/uvt/uni/univDetailSelection.do?menuId=PCUVTINF2000&searchSyr=2026&unvCd=0000233"],"candidateId":"CAND-fe04c1770a0d33bb"}]},{"optionId":"OPT27-c40b20b2b934dac9","entityId":"ENT27-f55565a5c6ed0882","department":"데이터사이언스학과","admissionName":"학생부 교과(기회균형선발 특별전형)","category":"학생부위주(교과)","connectionStatus":"review_required","connectionLabel":"명칭·전형 변경 가능성 검토","matchMethod":"manual_review_candidates","approvedYears":[],"approvedHistoryIds":[],"approvedHistoryUniversityCodes":[],"reviewCandidateCount":3,"candidates":[{"relation":"admission_changed_candidate","reviewStatus":"manual_review","matchMethod":"exact_department_changed_admission","score":0.93,"departmentScore":1.0,"admissionScore":0.75,"department":"데이터사이언스학과","admission":"기회균형전형","category":"학생부교과","historicalYears":["2026"],"historicalRecordIds":["ADIGA-0000233-2026-SUBJECT-5-7-데이터사이언스학과"],"historicalUniversityCodes":["0000233"],"sourceUrls":["https://www.adiga.kr/ucp/uvt/uni/univDetailSelection.do?menuId=PCUVTINF2000&searchSyr=2027&unvCd=0000233"],"candidateId":"CAND-c9d2e316b186ad8b"},{"relation":"admission_changed_candidate","reviewStatus":"manual_review","matchMethod":"exact_department_changed_admission","score":0.72,"departmentScore":1.0,"admissionScore":0.0,"department":"데이터사이언스학과","admission":"일반학생전형","category":"학생부교과","historicalYears":["2024","2025","2026"],"historicalRecordIds":["ADIGA-0000233-2024-SUBJECT-1-13-데이터사이언스학과","ADIGA-0000233-2025-SUBJECT-1-14-데이터사이언스학과","ADIGA-0000233-2026-SUBJECT-1-11-데이터사이언스학과"],"historicalUniversityCodes":["0000233"],"sourceUrls":["https://www.adiga.kr/ucp/uvt/uni/univDetailSelection.do?menuId=PCUVTINF2000&searchSyr=2025&unvCd=0000233","https://www.adiga.kr/ucp/uvt/uni/univDetailSelection.do?menuId=PCUVTINF2000&searchSyr=2026&unvCd=0000233","https://www.adiga.kr/ucp/uvt/uni/univDetailSelection.do?menuId=PCUVTINF2000&searchSyr=2027&unvCd=0000233"],"candidateId":"CAND-5810a250ab98fa35"},{"relation":"admission_changed_candidate","reviewStatus":"manual_review","matchMethod":"exact_department_changed_admission","score":0.72,"departmentScore":1.0,"admissionScore":0.0,"department":"데이터사이언스학과","admission":"특성화고교 졸업자전형","category":"학생부교과","historicalYears":["2025"],"historicalRecordIds":["ADIGA-0000233-2025-SUBJECT-2-4-데이터사이언스학과"],"historicalUniversityCodes":["0000233"],"sourceUrls":["https://www.adiga.kr/ucp/uvt/uni/univDetailSelection.do?menuId=PCUVTINF2000&searchSyr=2026&unvCd=0000233"],"candidateId":"CAND-3ed8c361b1d8d344"}]},{"optionId":"OPT27-95f52b2ee332fca0","entityId":"ENT27-4a2e976a46fcf385","department":"라이프스타일테크학과","admissionName":"학생부 교과 우수자전형","category":"학생부위주(교과)","connectionStatus":"review_required","connectionLabel":"명칭·전형 변경 가능성 검토","matchMethod":"manual_review_candidates","approvedYears":[],"approvedHistoryIds":[],"approvedHistoryUniversityCodes":[],"reviewCandidateCount":2,"candidates":[{"relation":"admission_changed_candidate","reviewStatus":"manual_review","matchMethod":"exact_department_changed_admission","score":0.72,"departmentScore":1.0,"admissionScore":0.0,"department":"라이프스타일테크학과","admission":"기회균형전형","category":"학생부교과","historicalYears":["2026"],"historicalRecordIds":["ADIGA-0000233-2026-SUBJECT-5-11-라이프스타일테크학과"],"historicalUniversityCodes":["0000233"],"sourceUrls":["https://www.adiga.kr/ucp/uvt/uni/univDetailSelection.do?menuId=PCUVTINF2000&searchSyr=2027&unvCd=0000233"],"candidateId":"CAND-fb8f63923d4fbdc3"},{"relation":"admission_changed_candidate","reviewStatus":"manual_review","matchMethod":"exact_department_changed_admission","score":0.72,"departmentScore":1.0,"admissionScore":0.0,"department":"라이프스타일테크학과","admission":"일반학생전형","category":"학생부교과","historicalYears":["2026"],"historicalRecordIds":["ADIGA-0000233-2026-SUBJECT-1-15-라이프스타일테크학과"],"historicalUniversityCodes":["0000233"],"sourceUrls":["https://www.adiga.kr/ucp/uvt/uni/univDetailSelection.do?menuId=PCUVTINF2000&searchSyr=2027&unvCd=0000233"],"candidateId":"CAND-afab5639823e02cc"}]},{"optionId":"OPT27-d15abe29e56354cb","entityId":"ENT27-29be9c8bbf5de31a","department":"바이오헬스케어학과","admissionName":"학생부 교과 우수자전형","category":"학생부위주(교과)","connectionStatus":"review_required","connectionLabel":"명칭·전형 변경 가능성 검토","matchMethod":"manual_review_candidates","approvedYears":[],"approvedHistoryIds":[],"approvedHistoryUniversityCodes":[],"reviewCandidateCount":2,"candidates":[{"relation":"admission_changed_candidate","reviewStatus":"manual_review","matchMethod":"exact_department_changed_admission","score":0.72,"departmentScore":1.0,"admissionScore":0.0,"department":"바이오헬스케어학과","admission":"기초생활수급자 및 차상위계층전형","category":"학생부교과","historicalYears":["2025"],"historicalRecordIds":["ADIGA-0000233-2025-SUBJECT-3-9-바이오헬스케어학과"],"historicalUniversityCodes":["0000233"],"sourceUrls":["https://www.adiga.kr/ucp/uvt/uni/univDetailSelection.do?menuId=PCUVTINF2000&searchSyr=2026&unvCd=0000233"],"candidateId":"CAND-c007d11f3586a336"},{"relation":"admission_changed_candidate","reviewStatus":"manual_review","matchMethod":"exact_department_changed_admission","score":0.72,"departmentScore":1.0,"admissionScore":0.0,"department":"바이오헬스케어학과","admission":"일반학생전형","category":"학생부교과","historicalYears":["2024","2025","2026"],"historicalRecordIds":["ADIGA-0000233-2024-SUBJECT-1-9-바이오헬스케어학과","ADIGA-0000233-2025-SUBJECT-1-12-바이오헬스케어학과","ADIGA-0000233-2026-SUBJECT-1-12-바이오헬스케어학과"],"historicalUniversityCodes":["0000233"],"sourceUrls":["https://www.adiga.kr/ucp/uvt/uni/univDetailSelection.do?menuId=PCUVTINF2000&searchSyr=2025&unvCd=0000233","https://www.adiga.kr/ucp/uvt/uni/univDetailSelection.do?menuId=PCUVTINF2000&searchSyr=2026&unvCd=0000233","https://www.adiga.kr/ucp/uvt/uni/univDetailSelection.do?menuId=PCUVTINF2000&searchSyr=2027&unvCd=0000233"],"candidateId":"CAND-d460d8671b571977"}]},{"optionId":"OPT27-1c350271561caf83","entityId":"ENT27-c74373421494fa1f","department":"바이오헬스케어학과","admissionName":"학생부 교과(기회균형선발 특별전형)","category":"학생부위주(교과)","connectionStatus":"review_required","connectionLabel":"명칭·전형 변경 가능성 검토","matchMethod":"manual_review_candidates","approvedYears":[],"approvedHistoryIds":[],"approvedHistoryUniversityCodes":[],"reviewCandidateCount":2,"candidates":[{"relation":"admission_changed_candidate","reviewStatus":"manual_review","matchMethod":"exact_department_changed_admission","score":0.72,"departmentScore":1.0,"admissionScore":0.0,"department":"바이오헬스케어학과","admission":"기초생활수급자 및 차상위계층전형","category":"학생부교과","historicalYears":["2025"],"historicalRecordIds":["ADIGA-0000233-2025-SUBJECT-3-9-바이오헬스케어학과"],"historicalUniversityCodes":["0000233"],"sourceUrls":["https://www.adiga.kr/ucp/uvt/uni/univDetailSelection.do?menuId=PCUVTINF2000&searchSyr=2026&unvCd=0000233"],"candidateId":"CAND-472e1a9d1004feb1"},{"relation":"admission_changed_candidate","reviewStatus":"manual_review","matchMethod":"exact_department_changed_admission","score":0.72,"departmentScore":1.0,"admissionScore":0.0,"department":"바이오헬스케어학과","admission":"일반학생전형","category":"학생부교과","historicalYears":["2024","2025","2026"],"historicalRecordIds":["ADIGA-0000233-2024-SUBJECT-1-9-바이오헬스케어학과","ADIGA-0000233-2025-SUBJECT-1-12-바이오헬스케어학과","ADIGA-0000233-2026-SUBJECT-1-12-바이오헬스케어학과"],"historicalUniversityCodes":["0000233"],"sourceUrls":["https://www.adiga.kr/ucp/uvt/uni/univDetailSelection.do?menuId=PCUVTINF2000&searchSyr=2025&unvCd=0000233","https://www.adiga.kr/ucp/uvt/uni/univDetailSelection.do?menuId=PCUVTINF2000&searchSyr=2026&unvCd=0000233","https://www.adiga.kr/ucp/uvt/uni/univDetailSelection.do?menuId=PCUVTINF2000&searchSyr=2027&unvCd=0000233"],"candidateId":"CAND-5dd2755c9f6eab7f"}]},{"optionId":"OPT27-78a20751dfa3ea14","entityId":"ENT27-cf1eed6b69db7fe4","department":"서비스디자인학과","admissionName":"학생부 교과 우수자전형","category":"학생부위주(교과)","connectionStatus":"review_required","connectionLabel":"명칭·전형 변경 가능성 검토","matchMethod":"manual_review_candidates","approvedYears":[],"approvedHistoryIds":[],"approvedHistoryUniversityCodes":[],"reviewCandidateCount":2,"candidates":[{"relation":"admission_changed_candidate","reviewStatus":"manual_review","matchMethod":"exact_department_changed_admission","score":0.72,"departmentScore":1.0,"admissionScore":0.0,"department":"서비스디자인학과","admission":"기회균형전형","category":"학생부교과","historicalYears":["2026"],"historicalRecordIds":["ADIGA-0000233-2026-SUBJECT-5-9-서비스디자인학과"],"historicalUniversityCodes":["0000233"],"sourceUrls":["https://www.adiga.kr/ucp/uvt/uni/univDetailSelection.do?menuId=PCUVTINF2000&searchSyr=2027&unvCd=0000233"],"candidateId":"CAND-7279064834351898"},{"relation":"admission_changed_candidate","reviewStatus":"manual_review","matchMethod":"exact_department_changed_admission","score":0.72,"departmentScore":1.0,"admissionScore":0.0,"department":"서비스디자인학과","admission":"일반학생전형","category":"학생부교과","historicalYears":["2024","2026"],"historicalRecordIds":["ADIGA-0000233-2024-SUBJECT-1-11-서비스디자인학과","ADIGA-0000233-2026-SUBJECT-1-14-서비스디자인학과"],"historicalUniversityCodes":["0000233"],"sourceUrls":["https://www.adiga.kr/ucp/uvt/uni/univDetailSelection.do?menuId=PCUVTINF2000&searchSyr=2025&unvCd=0000233","https://www.adiga.kr/ucp/uvt/uni/univDetailSelection.do?menuId=PCUVTINF2000&searchSyr=2027&unvCd=0000233"],"candidateId":"CAND-c60c74f46ea7bacc"}]},{"optionId":"OPT27-bc2aec8bae39ba23","entityId":"ENT27-644000d3ded42d06","department":"서비스디자인학과","admissionName":"학생부 교과(기회균형선발 특별전형)","category":"학생부위주(교과)","connectionStatus":"review_required","connectionLabel":"명칭·전형 변경 가능성 검토","matchMethod":"manual_review_candidates","approvedYears":[],"approvedHistoryIds":[],"approvedHistoryUniversityCodes":[],"reviewCandidateCount":2,"candidates":[{"relation":"admission_changed_candidate","reviewStatus":"manual_review","matchMethod":"exact_department_changed_admission","score":0.93,"departmentScore":1.0,"admissionScore":0.75,"department":"서비스디자인학과","admission":"기회균형전형","category":"학생부교과","historicalYears":["2026"],"historicalRecordIds":["ADIGA-0000233-2026-SUBJECT-5-9-서비스디자인학과"],"historicalUniversityCodes":["0000233"],"sourceUrls":["https://www.adiga.kr/ucp/uvt/uni/univDetailSelection.do?menuId=PCUVTINF2000&searchSyr=2027&unvCd=0000233"],"candidateId":"CAND-f713a75c2568552a"},{"relation":"admission_changed_candidate","reviewStatus":"manual_review","matchMethod":"exact_department_changed_admission","score":0.72,"departmentScore":1.0,"admissionScore":0.0,"department":"서비스디자인학과","admission":"일반학생전형","category":"학생부교과","historicalYears":["2024","2026"],"historicalRecordIds":["ADIGA-0000233-2024-SUBJECT-1-11-서비스디자인학과","ADIGA-0000233-2026-SUBJECT-1-14-서비스디자인학과"],"historicalUniversityCodes":["0000233"],"sourceUrls":["https://www.adiga.kr/ucp/uvt/uni/univDetailSelection.do?menuId=PCUVTINF2000&searchSyr=2025&unvCd=0000233","https://www.adiga.kr/ucp/uvt/uni/univDetailSelection.do?menuId=PCUVTINF2000&searchSyr=2027&unvCd=0000233"],"candidateId":"CAND-a4066dbb7cc3ea41"}]},{"optionId":"OPT27-4791f26dda8fcaf5","entityId":"ENT27-783df5ee8da2318d","department":"스포츠과학과","admissionName":"학생부 교과 우수자전형","category":"학생부위주(교과)","connectionStatus":"review_required","connectionLabel":"명칭·전형 변경 가능성 검토","matchMethod":"manual_review_candidates","approvedYears":[],"approvedHistoryIds":[],"approvedHistoryUniversityCodes":[],"reviewCandidateCount":2,"candidates":[{"relation":"admission_changed_candidate","reviewStatus":"manual_review","matchMethod":"exact_department_changed_admission","score":0.72,"departmentScore":1.0,"admissionScore":0.0,"department":"스포츠과학과","admission":"기회균형전형","category":"학생부교과","historicalYears":["2026"],"historicalRecordIds":["ADIGA-0000233-2026-SUBJECT-5-5-스포츠과학과"],"historicalUniversityCodes":["0000233"],"sourceUrls":["https://www.adiga.kr/ucp/uvt/uni/univDetailSelection.do?menuId=PCUVTINF2000&searchSyr=2027&unvCd=0000233"],"candidateId":"CAND-7a28da439498256a"},{"relation":"admission_changed_candidate","reviewStatus":"manual_review","matchMethod":"exact_department_changed_admission","score":0.72,"departmentScore":1.0,"admissionScore":0.0,"department":"스포츠과학과","admission":"일반학생전형","category":"학생부교과","historicalYears":["2026"],"historicalRecordIds":["ADIGA-0000233-2026-SUBJECT-1-8-스포츠과학과"],"historicalUniversityCodes":["0000233"],"sourceUrls":["https://www.adiga.kr/ucp/uvt/uni/univDetailSelection.do?menuId=PCUVTINF2000&searchSyr=2027&unvCd=0000233"],"candidateId":"CAND-b809c4e0796a9dcd"}]},{"optionId":"OPT27-be632185804918b6","entityId":"ENT27-1d84a744532fa2bf","department":"스포츠과학과","admissionName":"학생부 교과(기초생활수급자, 차상위계층, 한부모가족 지원 대상자 특별전형)","category":"학생부위주(교과)","connectionStatus":"review_required","connectionLabel":"명칭·전형 변경 가능성 검토","matchMethod":"manual_review_candidates","approvedYears":[],"approvedHistoryIds":[],"approvedHistoryUniversityCodes":[],"reviewCandidateCount":3,"candidates":[{"relation":"merged_candidate","reviewStatus":"manual_review","matchMethod":"multiple_historical_departments_for_current_option","score":0.7652,"departmentScore":0.8333,"admissionScore":0.6061,"department":"스포츠과학부 스포츠과학과","admission":"기초생활수급자 및 차상위계층전형","category":"학생부교과","historicalYears":["2025"],"historicalRecordIds":["ADIGA-0000233-2025-SUBJECT-3-7-스포츠과학부-스포츠과학과"],"historicalUniversityCodes":["0000233"],"sourceUrls":["https://www.adiga.kr/ucp/uvt/uni/univDetailSelection.do?menuId=PCUVTINF2000&searchSyr=2026&unvCd=0000233"],"candidateId":"CAND-a2460557b680ce44"},{"relation":"merged_candidate","reviewStatus":"manual_review","matchMethod":"multiple_historical_departments_for_current_option","score":0.72,"departmentScore":1.0,"admissionScore":0.0,"department":"스포츠과학과","admission":"기회균형전형","category":"학생부교과","historicalYears":["2026"],"historicalRecordIds":["ADIGA-0000233-2026-SUBJECT-5-5-스포츠과학과"],"historicalUniversityCodes":["0000233"],"sourceUrls":["https://www.adiga.kr/ucp/uvt/uni/univDetailSelection.do?menuId=PCUVTINF2000&searchSyr=2027&unvCd=0000233"],"candidateId":"CAND-b00c9ccc2554344f"},{"relation":"merged_candidate","reviewStatus":"manual_review","matchMethod":"multiple_historical_departments_for_current_option","score":0.72,"departmentScore":1.0,"admissionScore":0.0,"department":"스포츠과학과","admission":"일반학생전형","category":"학생부교과","historicalYears":["2026"],"historicalRecordIds":["ADIGA-0000233-2026-SUBJECT-1-8-스포츠과학과"],"historicalUniversityCodes":["0000233"],"sourceUrls":["https://www.adiga.kr/ucp/uvt/uni/univDetailSelection.do?menuId=PCUVTINF2000&searchSyr=2027&unvCd=0000233"],"candidateId":"CAND-40b9afaac8414084"}]},{"optionId":"OPT27-2d52e0c5036c4497","entityId":"ENT27-ced22c9192ba26c2","department":"스포츠과학과","admissionName":"학생부 교과(기회균형선발 특별전형)","category":"학생부위주(교과)","connectionStatus":"review_required","connectionLabel":"명칭·전형 변경 가능성 검토","matchMethod":"manual_review_candidates","approvedYears":[],"approvedHistoryIds":[],"approvedHistoryUniversityCodes":[],"reviewCandidateCount":2,"candidates":[{"relation":"admission_changed_candidate","reviewStatus":"manual_review","matchMethod":"exact_department_changed_admission","score":0.93,"departmentScore":1.0,"admissionScore":0.75,"department":"스포츠과학과","admission":"기회균형전형","category":"학생부교과","historicalYears":["2026"],"historicalRecordIds":["ADIGA-0000233-2026-SUBJECT-5-5-스포츠과학과"],"historicalUniversityCodes":["0000233"],"sourceUrls":["https://www.adiga.kr/ucp/uvt/uni/univDetailSelection.do?menuId=PCUVTINF2000&searchSyr=2027&unvCd=0000233"],"candidateId":"CAND-5e82b5166460fc02"},{"relation":"admission_changed_candidate","reviewStatus":"manual_review","matchMethod":"exact_department_changed_admission","score":0.72,"departmentScore":1.0,"admissionScore":0.0,"department":"스포츠과학과","admission":"일반학생전형","category":"학생부교과","historicalYears":["2026"],"historicalRecordIds":["ADIGA-0000233-2026-SUBJECT-1-8-스포츠과학과"],"historicalUniversityCodes":["0000233"],"sourceUrls":["https://www.adiga.kr/ucp/uvt/uni/univDetailSelection.do?menuId=PCUVTINF2000&searchSyr=2027&unvCd=0000233"],"candidateId":"CAND-3e289fe4949bba6f"}]},{"optionId":"OPT27-d47df14ce5befa6e","entityId":"ENT27-2c4f2f7273e1311e","department":"의료경영학과","admissionName":"학생부 교과 우수자전형","category":"학생부위주(교과)","connectionStatus":"review_required","connectionLabel":"명칭·전형 변경 가능성 검토","matchMethod":"manual_review_candidates","approvedYears":[],"approvedHistoryIds":[],"approvedHistoryUniversityCodes":[],"reviewCandidateCount":2,"candidates":[{"relation":"admission_changed_candidate","reviewStatus":"manual_review","matchMethod":"exact_department_changed_admission","score":0.72,"departmentScore":1.0,"admissionScore":0.0,"department":"의료경영학과","admission":"기초생활수급자 및 차상위계층전형","category":"학생부교과","historicalYears":["2025"],"historicalRecordIds":["ADIGA-0000233-2025-SUBJECT-3-4-의료경영학과"],"historicalUniversityCodes":["0000233"],"sourceUrls":["https://www.adiga.kr/ucp/uvt/uni/univDetailSelection.do?menuId=PCUVTINF2000&searchSyr=2026&unvCd=0000233"],"candidateId":"CAND-9068ad47541973cb"},{"relation":"admission_changed_candidate","reviewStatus":"manual_review","matchMethod":"exact_department_changed_admission","score":0.72,"departmentScore":1.0,"admissionScore":0.0,"department":"의료경영학과","admission":"일반학생전형","category":"학생부교과","historicalYears":["2024","2025","2026"],"historicalRecordIds":["ADIGA-0000233-2024-SUBJECT-1-8-의료경영학과","ADIGA-0000233-2025-SUBJECT-1-5-의료경영학과","ADIGA-0000233-2026-SUBJECT-1-9-의료경영학과"],"historicalUniversityCodes":["0000233"],"sourceUrls":["https://www.adiga.kr/ucp/uvt/uni/univDetailSelection.do?menuId=PCUVTINF2000&searchSyr=2025&unvCd=0000233","https://www.adiga.kr/ucp/uvt/uni/univDetailSelection.do?menuId=PCUVTINF2000&searchSyr=2026&unvCd=0000233","https://www.adiga.kr/ucp/uvt/uni/univDetailSelection.do?menuId=PCUVTINF2000&searchSyr=2027&unvCd=0000233"],"candidateId":"CAND-9b84e1790b3ad0ef"}]},{"optionId":"OPT27-91a94f8aa8d25e19","entityId":"ENT27-4654b4664873c5a8","department":"의료경영학과","admissionName":"학생부 교과(기회균형선발 특별전형)","category":"학생부위주(교과)","connectionStatus":"review_required","connectionLabel":"명칭·전형 변경 가능성 검토","matchMethod":"manual_review_candidates","approvedYears":[],"approvedHistoryIds":[],"approvedHistoryUniversityCodes":[],"reviewCandidateCount":2,"candidates":[{"relation":"admission_changed_candidate","reviewStatus":"manual_review","matchMethod":"exact_department_changed_admission","score":0.72,"departmentScore":1.0,"admissionScore":0.0,"department":"의료경영학과","admission":"기초생활수급자 및 차상위계층전형","category":"학생부교과","historicalYears":["2025"],"historicalRecordIds":["ADIGA-0000233-2025-SUBJECT-3-4-의료경영학과"],"historicalUniversityCodes":["0000233"],"sourceUrls":["https://www.adiga.kr/ucp/uvt/uni/univDetailSelection.do?menuId=PCUVTINF2000&searchSyr=2026&unvCd=0000233"],"candidateId":"CAND-562bfbfb45663397"},{"relation":"admission_changed_candidate","reviewStatus":"manual_review","matchMethod":"exact_department_changed_admission","score":0.72,"departmentScore":1.0,"admissionScore":0.0,"department":"의료경영학과","admission":"일반학생전형","category":"학생부교과","historicalYears":["2024","2025","2026"],"historicalRecordIds":["ADIGA-0000233-2024-SUBJECT-1-8-의료경영학과","ADIGA-0000233-2025-SUBJECT-1-5-의료경영학과","ADIGA-0000233-2026-SUBJECT-1-9-의료경영학과"],"historicalUniversityCodes":["0000233"],"sourceUrls":["https://www.adiga.kr/ucp/uvt/uni/univDetailSelection.do?menuId=PCUVTINF2000&searchSyr=2025&unvCd=0000233","https://www.adiga.kr/ucp/uvt/uni/univDetailSelection.do?menuId=PCUVTINF2000&searchSyr=2026&unvCd=0000233","https://www.adiga.kr/ucp/uvt/uni/univDetailSelection.do?menuId=PCUVTINF2000&searchSyr=2027&unvCd=0000233"],"candidateId":"CAND-901e5cdf4dfd0c5b"}]},{"optionId":"OPT27-925c76582584fded","entityId":"ENT27-953c7ed47db4447e","department":"의료경영학과","admissionName":"학생부 교과(특성화고교 졸업자 특별전형)","category":"학생부위주(교과)","connectionStatus":"review_required","connectionLabel":"명칭·전형 변경 가능성 검토","matchMethod":"manual_review_candidates","approvedYears":[],"approvedHistoryIds":[],"approvedHistoryUniversityCodes":[],"reviewCandidateCount":2,"candidates":[{"relation":"admission_changed_candidate","reviewStatus":"manual_review","matchMethod":"exact_department_changed_admission","score":0.72,"departmentScore":1.0,"admissionScore":0.0,"department":"의료경영학과","admission":"기초생활수급자 및 차상위계층전형","category":"학생부교과","historicalYears":["2025"],"historicalRecordIds":["ADIGA-0000233-2025-SUBJECT-3-4-의료경영학과"],"historicalUniversityCodes":["0000233"],"sourceUrls":["https://www.adiga.kr/ucp/uvt/uni/univDetailSelection.do?menuId=PCUVTINF2000&searchSyr=2026&unvCd=0000233"],"candidateId":"CAND-9001b4548c70ea40"},{"relation":"admission_changed_candidate","reviewStatus":"manual_review","matchMethod":"exact_department_changed_admission","score":0.72,"departmentScore":1.0,"admissionScore":0.0,"department":"의료경영학과","admission":"일반학생전형","category":"학생부교과","historicalYears":["2024","2025","2026"],"historicalRecordIds":["ADIGA-0000233-2024-SUBJECT-1-8-의료경영학과","ADIGA-0000233-2025-SUBJECT-1-5-의료경영학과","ADIGA-0000233-2026-SUBJECT-1-9-의료경영학과"],"historicalUniversityCodes":["0000233"],"sourceUrls":["https://www.adiga.kr/ucp/uvt/uni/univDetailSelection.do?menuId=PCUVTINF2000&searchSyr=2025&unvCd=0000233","https://www.adiga.kr/ucp/uvt/uni/univDetailSelection.do?menuId=PCUVTINF2000&searchSyr=2026&unvCd=0000233","https://www.adiga.kr/ucp/uvt/uni/univDetailSelection.do?menuId=PCUVTINF2000&searchSyr=2027&unvCd=0000233"],"candidateId":"CAND-dac2ad661c21c627"}]},{"optionId":"OPT27-b769892e30cba0de","entityId":"ENT27-c9877eea1cb1fadf","department":"의료사회복지학과","admissionName":"학생부 교과 우수자전형","category":"학생부위주(교과)","connectionStatus":"review_required","connectionLabel":"명칭·전형 변경 가능성 검토","matchMethod":"manual_review_candidates","approvedYears":[],"approvedHistoryIds":[],"approvedHistoryUniversityCodes":[],"reviewCandidateCount":2,"candidates":[{"relation":"admission_changed_candidate","reviewStatus":"manual_review","matchMethod":"exact_department_changed_admission","score":0.72,"departmentScore":1.0,"admissionScore":0.0,"department":"의료사회복지학과","admission":"기회균형전형","category":"학생부교과","historicalYears":["2026"],"historicalRecordIds":["ADIGA-0000233-2026-SUBJECT-5-6-의료사회복지학과"],"historicalUniversityCodes":["0000233"],"sourceUrls":["https://www.adiga.kr/ucp/uvt/uni/univDetailSelection.do?menuId=PCUVTINF2000&searchSyr=2027&unvCd=0000233"],"candidateId":"CAND-da398f0a2703aba4"},{"relation":"admission_changed_candidate","reviewStatus":"manual_review","matchMethod":"exact_department_changed_admission","score":0.72,"departmentScore":1.0,"admissionScore":0.0,"department":"의료사회복지학과","admission":"일반학생전형","category":"학생부교과","historicalYears":["2025","2026"],"historicalRecordIds":["ADIGA-0000233-2025-SUBJECT-1-6-의료사회복지학과","ADIGA-0000233-2026-SUBJECT-1-7-의료사회복지학과"],"historicalUniversityCodes":["0000233"],"sourceUrls":["https://www.adiga.kr/ucp/uvt/uni/univDetailSelection.do?menuId=PCUVTINF2000&searchSyr=2026&unvCd=0000233","https://www.adiga.kr/ucp/uvt/uni/univDetailSelection.do?menuId=PCUVTINF2000&searchSyr=2027&unvCd=0000233"],"candidateId":"CAND-ea298486bc6fde03"}]},{"optionId":"OPT27-f5fcc37d051cce62","entityId":"ENT27-40e085e1bcf6f4ac","department":"의료사회복지학과","admissionName":"학생부 교과(기회균형선발 특별전형)","category":"학생부위주(교과)","connectionStatus":"review_required","connectionLabel":"명칭·전형 변경 가능성 검토","matchMethod":"manual_review_candidates","approvedYears":[],"approvedHistoryIds":[],"approvedHistoryUniversityCodes":[],"reviewCandidateCount":2,"candidates":[{"relation":"admission_changed_candidate","reviewStatus":"manual_review","matchMethod":"exact_department_changed_admission","score":0.93,"departmentScore":1.0,"admissionScore":0.75,"department":"의료사회복지학과","admission":"기회균형전형","category":"학생부교과","historicalYears":["2026"],"historicalRecordIds":["ADIGA-0000233-2026-SUBJECT-5-6-의료사회복지학과"],"historicalUniversityCodes":["0000233"],"sourceUrls":["https://www.adiga.kr/ucp/uvt/uni/univDetailSelection.do?menuId=PCUVTINF2000&searchSyr=2027&unvCd=0000233"],"candidateId":"CAND-9a8d1249b7f3cf1d"},{"relation":"admission_changed_candidate","reviewStatus":"manual_review","matchMethod":"exact_department_changed_admission","score":0.72,"departmentScore":1.0,"admissionScore":0.0,"department":"의료사회복지학과","admission":"일반학생전형","category":"학생부교과","historicalYears":["2025","2026"],"historicalRecordIds":["ADIGA-0000233-2025-SUBJECT-1-6-의료사회복지학과","ADIGA-0000233-2026-SUBJECT-1-7-의료사회복지학과"],"historicalUniversityCodes":["0000233"],"sourceUrls":["https://www.adiga.kr/ucp/uvt/uni/univDetailSelection.do?menuId=PCUVTINF2000&searchSyr=2026&unvCd=0000233","https://www.adiga.kr/ucp/uvt/uni/univDetailSelection.do?menuId=PCUVTINF2000&searchSyr=2027&unvCd=0000233"],"candidateId":"CAND-0754ce43e4e288ae"}]},{"optionId":"OPT27-cd9fe66d7a6b4dae","entityId":"ENT27-973282922406140b","department":"의료심리학과","admissionName":"학생부 교과 우수자전형","category":"학생부위주(교과)","connectionStatus":"review_required","connectionLabel":"명칭·전형 변경 가능성 검토","matchMethod":"manual_review_candidates","approvedYears":[],"approvedHistoryIds":[],"approvedHistoryUniversityCodes":[],"reviewCandidateCount":3,"candidates":[{"relation":"admission_changed_candidate","reviewStatus":"manual_review","matchMethod":"exact_department_changed_admission","score":0.72,"departmentScore":1.0,"admissionScore":0.0,"department":"의료심리학과","admission":"기초생활수급자 및 차상위계층전형","category":"학생부교과","historicalYears":["2025"],"historicalRecordIds":["ADIGA-0000233-2025-SUBJECT-3-10-의료심리학과"],"historicalUniversityCodes":["0000233"],"sourceUrls":["https://www.adiga.kr/ucp/uvt/uni/univDetailSelection.do?menuId=PCUVTINF2000&searchSyr=2026&unvCd=0000233"],"candidateId":"CAND-e09b01230cec9a54"},{"relation":"admission_changed_candidate","reviewStatus":"manual_review","matchMethod":"exact_department_changed_admission","score":0.72,"departmentScore":1.0,"admissionScore":0.0,"department":"의료심리학과","admission":"기회균형전형","category":"학생부교과","historicalYears":["2026"],"historicalRecordIds":["ADIGA-0000233-2026-SUBJECT-5-8-의료심리학과"],"historicalUniversityCodes":["0000233"],"sourceUrls":["https://www.adiga.kr/ucp/uvt/uni/univDetailSelection.do?menuId=PCUVTINF2000&searchSyr=2027&unvCd=0000233"],"candidateId":"CAND-c13761ea8bc86303"},{"relation":"admission_changed_candidate","reviewStatus":"manual_review","matchMethod":"exact_department_changed_admission","score":0.72,"departmentScore":1.0,"admissionScore":0.0,"department":"의료심리학과","admission":"일반학생전형","category":"학생부교과","historicalYears":["2024","2025","2026"],"historicalRecordIds":["ADIGA-0000233-2024-SUBJECT-1-10-의료심리학과","ADIGA-0000233-2025-SUBJECT-1-13-의료심리학과","ADIGA-0000233-2026-SUBJECT-1-13-의료심리학과"],"historicalUniversityCodes":["0000233"],"sourceUrls":["https://www.adiga.kr/ucp/uvt/uni/univDetailSelection.do?menuId=PCUVTINF2000&searchSyr=2025&unvCd=0000233","https://www.adiga.kr/ucp/uvt/uni/univDetailSelection.do?menuId=PCUVTINF2000&searchSyr=2026&unvCd=0000233","https://www.adiga.kr/ucp/uvt/uni/univDetailSelection.do?menuId=PCUVTINF2000&searchSyr=2027&unvCd=0000233"],"candidateId":"CAND-7a3fa4931eb95a6c"}]},{"optionId":"OPT27-830aafd43d5ba7a8","entityId":"ENT27-6b52cefca21e6bd3","department":"의료심리학과","admissionName":"학생부 교과(기회균형선발 특별전형)","category":"학생부위주(교과)","connectionStatus":"review_required","connectionLabel":"명칭·전형 변경 가능성 검토","matchMethod":"manual_review_candidates","approvedYears":[],"approvedHistoryIds":[],"approvedHistoryUniversityCodes":[],"reviewCandidateCount":3,"candidates":[{"relation":"admission_changed_candidate","reviewStatus":"manual_review","matchMethod":"exact_department_changed_admission","score":0.93,"departmentScore":1.0,"admissionScore":0.75,"department":"의료심리학과","admission":"기회균형전형","category":"학생부교과","historicalYears":["2026"],"historicalRecordIds":["ADIGA-0000233-2026-SUBJECT-5-8-의료심리학과"],"historicalUniversityCodes":["0000233"],"sourceUrls":["https://www.adiga.kr/ucp/uvt/uni/univDetailSelection.do?menuId=PCUVTINF2000&searchSyr=2027&unvCd=0000233"],"candidateId":"CAND-5cad41eeca360139"},{"relation":"admission_changed_candidate","reviewStatus":"manual_review","matchMethod":"exact_department_changed_admission","score":0.72,"departmentScore":1.0,"admissionScore":0.0,"department":"의료심리학과","admission":"기초생활수급자 및 차상위계층전형","category":"학생부교과","historicalYears":["2025"],"historicalRecordIds":["ADIGA-0000233-2025-SUBJECT-3-10-의료심리학과"],"historicalUniversityCodes":["0000233"],"sourceUrls":["https://www.adiga.kr/ucp/uvt/uni/univDetailSelection.do?menuId=PCUVTINF2000&searchSyr=2026&unvCd=0000233"],"candidateId":"CAND-939440187e8d831c"},{"relation":"admission_changed_candidate","reviewStatus":"manual_review","matchMethod":"exact_department_changed_admission","score":0.72,"departmentScore":1.0,"admissionScore":0.0,"department":"의료심리학과","admission":"일반학생전형","category":"학생부교과","historicalYears":["2024","2025","2026"],"historicalRecordIds":["ADIGA-0000233-2024-SUBJECT-1-10-의료심리학과","ADIGA-0000233-2025-SUBJECT-1-13-의료심리학과","ADIGA-0000233-2026-SUBJECT-1-13-의료심리학과"],"historicalUniversityCodes":["0000233"],"sourceUrls":["https://www.adiga.kr/ucp/uvt/uni/univDetailSelection.do?menuId=PCUVTINF2000&searchSyr=2025&unvCd=0000233","https://www.adiga.kr/ucp/uvt/uni/univDetailSelection.do?menuId=PCUVTINF2000&searchSyr=2026&unvCd=0000233","https://www.adiga.kr/ucp/uvt/uni/univDetailSelection.do?menuId=PCUVTINF2000&searchSyr=2027&unvCd=0000233"],"candidateId":"CAND-b93bf8545a634368"}]},{"optionId":"OPT27-2ec23fcb8bd969e6","entityId":"ENT27-573225712f079349","department":"의생명과학과","admissionName":"학생부 교과 우수자전형","category":"학생부위주(교과)","connectionStatus":"review_required","connectionLabel":"명칭·전형 변경 가능성 검토","matchMethod":"manual_review_candidates","approvedYears":[],"approvedHistoryIds":[],"approvedHistoryUniversityCodes":[],"reviewCandidateCount":2,"candidates":[{"relation":"admission_changed_candidate","reviewStatus":"manual_review","matchMethod":"exact_department_changed_admission","score":0.72,"departmentScore":1.0,"admissionScore":0.0,"department":"의생명과학과","admission":"기회균형전형","category":"학생부교과","historicalYears":["2026"],"historicalRecordIds":["ADIGA-0000233-2026-SUBJECT-5-12-의생명과학과"],"historicalUniversityCodes":["0000233"],"sourceUrls":["https://www.adiga.kr/ucp/uvt/uni/univDetailSelection.do?menuId=PCUVTINF2000&searchSyr=2027&unvCd=0000233"],"candidateId":"CAND-d9999331b18445a7"},{"relation":"admission_changed_candidate","reviewStatus":"manual_review","matchMethod":"exact_department_changed_admission","score":0.72,"departmentScore":1.0,"admissionScore":0.0,"department":"의생명과학과","admission":"일반학생전형","category":"학생부교과","historicalYears":["2024","2025","2026"],"historicalRecordIds":["ADIGA-0000233-2024-SUBJECT-1-5-의생명과학과","ADIGA-0000233-2025-SUBJECT-1-8-의생명과학과","ADIGA-0000233-2026-SUBJECT-1-5-의생명과학과"],"historicalUniversityCodes":["0000233"],"sourceUrls":["https://www.adiga.kr/ucp/uvt/uni/univDetailSelection.do?menuId=PCUVTINF2000&searchSyr=2025&unvCd=0000233","https://www.adiga.kr/ucp/uvt/uni/univDetailSelection.do?menuId=PCUVTINF2000&searchSyr=2026&unvCd=0000233","https://www.adiga.kr/ucp/uvt/uni/univDetailSelection.do?menuId=PCUVTINF2000&searchSyr=2027&unvCd=0000233"],"candidateId":"CAND-987d55e0a2b7e2ff"}]},{"optionId":"OPT27-705f0eb760851254","entityId":"ENT27-0187d0122924c16a","department":"의생명과학과","admissionName":"학생부 교과(기초생활수급자, 차상위계층, 한부모가족 지원 대상자 특별전형)","category":"학생부위주(교과)","connectionStatus":"review_required","connectionLabel":"명칭·전형 변경 가능성 검토","matchMethod":"manual_review_candidates","approvedYears":[],"approvedHistoryIds":[],"approvedHistoryUniversityCodes":[],"reviewCandidateCount":2,"candidates":[{"relation":"admission_changed_candidate","reviewStatus":"manual_review","matchMethod":"exact_department_changed_admission","score":0.72,"departmentScore":1.0,"admissionScore":0.0,"department":"의생명과학과","admission":"기회균형전형","category":"학생부교과","historicalYears":["2026"],"historicalRecordIds":["ADIGA-0000233-2026-SUBJECT-5-12-의생명과학과"],"historicalUniversityCodes":["0000233"],"sourceUrls":["https://www.adiga.kr/ucp/uvt/uni/univDetailSelection.do?menuId=PCUVTINF2000&searchSyr=2027&unvCd=0000233"],"candidateId":"CAND-90d45e52d278ece0"},{"relation":"admission_changed_candidate","reviewStatus":"manual_review","matchMethod":"exact_department_changed_admission","score":0.72,"departmentScore":1.0,"admissionScore":0.0,"department":"의생명과학과","admission":"일반학생전형","category":"학생부교과","historicalYears":["2024","2025","2026"],"historicalRecordIds":["ADIGA-0000233-2024-SUBJECT-1-5-의생명과학과","ADIGA-0000233-2025-SUBJECT-1-8-의생명과학과","ADIGA-0000233-2026-SUBJECT-1-5-의생명과학과"],"historicalUniversityCodes":["0000233"],"sourceUrls":["https://www.adiga.kr/ucp/uvt/uni/univDetailSelection.do?menuId=PCUVTINF2000&searchSyr=2025&unvCd=0000233","https://www.adiga.kr/ucp/uvt/uni/univDetailSelection.do?menuId=PCUVTINF2000&searchSyr=2026&unvCd=0000233","https://www.adiga.kr/ucp/uvt/uni/univDetailSelection.do?menuId=PCUVTINF2000&searchSyr=2027&unvCd=0000233"],"candidateId":"CAND-c322903aa73d1991"}]},{"optionId":"OPT27-d5ed33e939d8bca5","entityId":"ENT27-7877267026bbff04","department":"의생명과학과","admissionName":"학생부 교과(기회균형선발 특별전형)","category":"학생부위주(교과)","connectionStatus":"review_required","connectionLabel":"명칭·전형 변경 가능성 검토","matchMethod":"manual_review_candidates","approvedYears":[],"approvedHistoryIds":[],"approvedHistoryUniversityCodes":[],"reviewCandidateCount":2,"candidates":[{"relation":"admission_changed_candidate","reviewStatus":"manual_review","matchMethod":"exact_department_changed_admission","score":0.93,"departmentScore":1.0,"admissionScore":0.75,"department":"의생명과학과","admission":"기회균형전형","category":"학생부교과","historicalYears":["2026"],"historicalRecordIds":["ADIGA-0000233-2026-SUBJECT-5-12-의생명과학과"],"historicalUniversityCodes":["0000233"],"sourceUrls":["https://www.adiga.kr/ucp/uvt/uni/univDetailSelection.do?menuId=PCUVTINF2000&searchSyr=2027&unvCd=0000233"],"candidateId":"CAND-7de1e6863b69f6e5"},{"relation":"admission_changed_candidate","reviewStatus":"manual_review","matchMethod":"exact_department_changed_admission","score":0.72,"departmentScore":1.0,"admissionScore":0.0,"department":"의생명과학과","admission":"일반학생전형","category":"학생부교과","historicalYears":["2024","2025","2026"],"historicalRecordIds":["ADIGA-0000233-2024-SUBJECT-1-5-의생명과학과","ADIGA-0000233-2025-SUBJECT-1-8-의생명과학과","ADIGA-0000233-2026-SUBJECT-1-5-의생명과학과"],"historicalUniversityCodes":["0000233"],"sourceUrls":["https://www.adiga.kr/ucp/uvt/uni/univDetailSelection.do?menuId=PCUVTINF2000&searchSyr=2025&unvCd=0000233","https://www.adiga.kr/ucp/uvt/uni/univDetailSelection.do?menuId=PCUVTINF2000&searchSyr=2026&unvCd=0000233","https://www.adiga.kr/ucp/uvt/uni/univDetailSelection.do?menuId=PCUVTINF2000&searchSyr=2027&unvCd=0000233"],"candidateId":"CAND-4e89f84c812a5e47"}]},{"optionId":"OPT27-775c4c600bdabfeb","entityId":"ENT27-0d7b612342ef4ec1","department":"태권도학과","admissionName":"실기/실적(전공관련우수자특별전형)","category":"실기/실적위주","connectionStatus":"new_candidate","connectionLabel":"2027 신설 가능성·과거 입결 없음","matchMethod":"no_historical_candidate","approvedYears":[],"approvedHistoryIds":[],"approvedHistoryUniversityCodes":[],"reviewCandidateCount":0,"candidates":[]},{"optionId":"OPT27-1198e1a1d2083fa9","entityId":"ENT27-8e20418c6b74bf96","department":"태권도학과","admissionName":"학생부 교과 우수자전형","category":"학생부위주(교과)","connectionStatus":"review_required","connectionLabel":"명칭·전형 변경 가능성 검토","matchMethod":"manual_review_candidates","approvedYears":[],"approvedHistoryIds":[],"approvedHistoryUniversityCodes":[],"reviewCandidateCount":2,"candidates":[{"relation":"admission_changed_candidate","reviewStatus":"manual_review","matchMethod":"exact_department_changed_admission","score":0.72,"departmentScore":1.0,"admissionScore":0.0,"department":"태권도학과","admission":"기회균형전형","category":"학생부교과","historicalYears":["2026"],"historicalRecordIds":["ADIGA-0000233-2026-SUBJECT-5-4-태권도학과"],"historicalUniversityCodes":["0000233"],"sourceUrls":["https://www.adiga.kr/ucp/uvt/uni/univDetailSelection.do?menuId=PCUVTINF2000&searchSyr=2027&unvCd=0000233"],"candidateId":"CAND-080ddbb1837d5b8b"},{"relation":"admission_changed_candidate","reviewStatus":"manual_review","matchMethod":"exact_department_changed_admission","score":0.72,"departmentScore":1.0,"admissionScore":0.0,"department":"태권도학과","admission":"일반학생전형","category":"학생부교과","historicalYears":["2026"],"historicalRecordIds":["ADIGA-0000233-2026-SUBJECT-1-6-태권도학과"],"historicalUniversityCodes":["0000233"],"sourceUrls":["https://www.adiga.kr/ucp/uvt/uni/univDetailSelection.do?menuId=PCUVTINF2000&searchSyr=2027&unvCd=0000233"],"candidateId":"CAND-8bcf2ab8cd44c9d2"}]},{"optionId":"OPT27-744efa0bb79fd109","entityId":"ENT27-44c5dca10ccf7d20","department":"태권도학과","admissionName":"학생부 교과(기회균형선발 특별전형)","category":"학생부위주(교과)","connectionStatus":"review_required","connectionLabel":"명칭·전형 변경 가능성 검토","matchMethod":"manual_review_candidates","approvedYears":[],"approvedHistoryIds":[],"approvedHistoryUniversityCodes":[],"reviewCandidateCount":2,"candidates":[{"relation":"admission_changed_candidate","reviewStatus":"manual_review","matchMethod":"exact_department_changed_admission","score":0.93,"departmentScore":1.0,"admissionScore":0.75,"department":"태권도학과","admission":"기회균형전형","category":"학생부교과","historicalYears":["2026"],"historicalRecordIds":["ADIGA-0000233-2026-SUBJECT-5-4-태권도학과"],"historicalUniversityCodes":["0000233"],"sourceUrls":["https://www.adiga.kr/ucp/uvt/uni/univDetailSelection.do?menuId=PCUVTINF2000&searchSyr=2027&unvCd=0000233"],"candidateId":"CAND-bddc4ded340315d2"},{"relation":"admission_changed_candidate","reviewStatus":"manual_review","matchMethod":"exact_department_changed_admission","score":0.72,"departmentScore":1.0,"admissionScore":0.0,"department":"태권도학과","admission":"일반학생전형","category":"학생부교과","historicalYears":["2026"],"historicalRecordIds":["ADIGA-0000233-2026-SUBJECT-1-6-태권도학과"],"historicalUniversityCodes":["0000233"],"sourceUrls":["https://www.adiga.kr/ucp/uvt/uni/univDetailSelection.do?menuId=PCUVTINF2000&searchSyr=2027&unvCd=0000233"],"candidateId":"CAND-731f32f6034d4762"}]}],"generatedAt":"2026-07-19T06:13:48+00:00"}